benchmarks/README.md
benchmarks/TEST_RESOURCES_HASH.txt
benchmarks/benchmark_simulariumio.py
benchmarks/download_benchmark_resources.py
benchmarks/upload_benchmark_resources.py
docs/conf.py
docs/contributing.rst
docs/index.rst
docs/installation.rst
docs/modules.rst
examples/Tutorial_cellpack.ipynb
examples/Tutorial_custom.ipynb
examples/Tutorial_cytosim.ipynb
examples/Tutorial_filters.ipynb
examples/Tutorial_mcell.ipynb
examples/Tutorial_md.ipynb
examples/Tutorial_medyan.ipynb
examples/Tutorial_mem3dg.ipynb
examples/Tutorial_nerdss.ipynb
examples/Tutorial_physicell.ipynb
examples/Tutorial_plots.ipynb
examples/Tutorial_readdy.ipynb
examples/Tutorial_smoldyn.ipynb
examples/Tutorial_springsalad.ipynb
examples/__init__.py
examples/img/drag_drop.gif
simulariumio/__init__.py
simulariumio/constants.py
simulariumio/exceptions.py
simulariumio/file_converter.py
simulariumio/trajectory_converter.py
simulariumio/utils.py
simulariumio/cellpack/__init__.py
simulariumio/cellpack/cellpack_converter.py
simulariumio/cellpack/cellpack_data.py
simulariumio/cytosim/__init__.py
simulariumio/cytosim/cytosim_converter.py
simulariumio/cytosim/cytosim_data.py
simulariumio/cytosim/cytosim_object_info.py
simulariumio/data_objects/__init__.py
simulariumio/data_objects/agent_data.py
simulariumio/data_objects/binary_data.py
simulariumio/data_objects/camera_data.py
simulariumio/data_objects/dimension_data.py
simulariumio/data_objects/display_data.py
simulariumio/data_objects/frame_data.py
simulariumio/data_objects/histogram_plot_data.py
simulariumio/data_objects/input_file_data.py
simulariumio/data_objects/json_data.py
simulariumio/data_objects/meta_data.py
simulariumio/data_objects/model_meta_data.py
simulariumio/data_objects/scatter_plot_data.py
simulariumio/data_objects/simularium_file_data.py
simulariumio/data_objects/trajectory_data.py
simulariumio/data_objects/unit_data.py
simulariumio/filters/__init__.py
simulariumio/filters/add_agents_filter.py
simulariumio-1.13.0.dist-info/licenses/LICENSE
simulariumio-1.13.0.dist-info/METADATA
simulariumio-1.13.0.dist-info/WHEEL
simulariumio-1.13.0.dist-info/top_level.txt
simulariumio-1.13.0.dist-info/RECORD
