Metadata-Version: 2.4
Name: simulariumio
Version: 1.13.0
Summary: Python package that converts simulation outputs to the format consumed by the Simularium viewer website
Author-email: Blair Lyons <blairl@alleninstitute.org>
License: Apache Software License 2.0
Project-URL: Homepage, https://github.com/Simularium/simulariumio
Project-URL: Bug Tracker, https://github.com/Simularium/simulariumio/issues
Project-URL: Documentation, https://Simularium.github.io/simulariumio
Project-URL: User Support, https://github.com/Simularium/simulariumio/issues
Classifier: Development Status :: 4 - Beta
Classifier: Natural Language :: English
Classifier: Programming Language :: Python :: 3.7
Classifier: Programming Language :: Python :: 3.8
Classifier: Programming Language :: Python :: 3.9
Requires-Python: >=3.8
License-File: LICENSE
Requires-Dist: numpy>=1.19.0
Requires-Dist: pandas>=1.1.2
Requires-Dist: pint>=0.17
Provides-Extra: mcell
Requires-Dist: scipy>=1.5.2; extra == "mcell"
Provides-Extra: physicell
Requires-Dist: scipy>=1.5.2; extra == "physicell"
Provides-Extra: md
Requires-Dist: MDAnalysis>=2.0.0; extra == "md"
Requires-Dist: MDAnalysisTests>=2.0.0; extra == "md"
Provides-Extra: cellpack
Requires-Dist: cellpack==1.0.3; extra == "cellpack"
Provides-Extra: nerdss
Requires-Dist: MDAnalysis>=2.0.0; extra == "nerdss"
Provides-Extra: mem3dg
Requires-Dist: netCDF4; extra == "mem3dg"
Provides-Extra: tutorial
Requires-Dist: jupyter; extra == "tutorial"
Requires-Dist: scipy>=1.5.2; extra == "tutorial"
Requires-Dist: MDAnalysis>=2.0.0; extra == "tutorial"
Requires-Dist: MDAnalysisTests>=2.0.0; extra == "tutorial"
Provides-Extra: benchmark
Requires-Dist: awscli>=1.20; extra == "benchmark"
Requires-Dist: quilt3; extra == "benchmark"
Provides-Extra: lint
Requires-Dist: black>=22.3.0; extra == "lint"
Requires-Dist: check-manifest>=0.48; extra == "lint"
Requires-Dist: flake8>=3.8.3; extra == "lint"
Requires-Dist: flake8-debugger>=3.2.1; extra == "lint"
Requires-Dist: flake8-typing-imports>=1.9.0; extra == "lint"
Requires-Dist: isort>=5.7.0; extra == "lint"
Requires-Dist: mypy>=0.790; extra == "lint"
Requires-Dist: pre-commit>=2.20.0; extra == "lint"
Provides-Extra: test
Requires-Dist: coverage>=5.1; extra == "test"
Requires-Dist: pytest>=5.4.3; extra == "test"
Requires-Dist: pytest-cov>=2.9.0; extra == "test"
Requires-Dist: pytest-raises>=0.11; extra == "test"
Requires-Dist: nbmake; extra == "test"
Provides-Extra: docs
Requires-Dist: m2r2>=0.2.7; extra == "docs"
Requires-Dist: Sphinx>=4.0.0; extra == "docs"
Requires-Dist: furo>=2022.4.7; extra == "docs"
Requires-Dist: numpydoc; extra == "docs"
Requires-Dist: sphinx-copybutton; extra == "docs"
Requires-Dist: docutils<0.19,>=0.18; extra == "docs"
Provides-Extra: dev
Requires-Dist: ipython; extra == "dev"
Dynamic: license-file
